kioss/__init__.py
kioss/_pipe.py
kioss/_util.py
kioss/py.typed
kioss/_execution/__init__.py
kioss/_execution/_concurrency.py
kioss/_execution/_core.py
kioss/_visit/__init__.py
kioss/_visit/_base.py
kioss/_visit/_explanation.py
kioss/_visit/_iter.py
tests/__init__.py
tests/test_legacy.py
tests/test_pipe.py
tests/test_util.py
kioss-0.9.1.dist-info/LICENSE
kioss-0.9.1.dist-info/METADATA
kioss-0.9.1.dist-info/WHEEL
kioss-0.9.1.dist-info/top_level.txt
kioss-0.9.1.dist-info/RECORD
